dscript/__init__.py
dscript/__main__.py
dscript/alphabets.py
dscript/fasta.py
dscript/foldseek.py
dscript/glider.py
dscript/language_model.py
dscript/load_worker.py
dscript/loading.py
dscript/pretrained.py
dscript/utils.py
dscript/commands/__init__.py
dscript/commands/embed.py
dscript/commands/evaluate.py
dscript/commands/extract_3di.py
dscript/commands/par_worker.py
dscript/commands/par_writer.py
dscript/commands/predict_bipartite.py
dscript/commands/predict_block.py
dscript/commands/predict_serial.py
dscript/commands/train.py
dscript/models/__init__.py
dscript/models/contact.py
dscript/models/embedding.py
dscript/models/interaction.py
dscript/tests/test_alphabets.py
dscript/tests/test_commands.py
dscript/tests/test_fasta.py
dscript/tests/test_foldseek.py
dscript/tests/test_language_model.py
dscript/tests/test_models_contact.py
dscript/tests/test_models_embedding.py
dscript/tests/test_models_interaction.py
dscript/tests/test_pretrained.py
dscript-0.3.1.dist-info/licenses/LICENSE
dscript-0.3.1.dist-info/METADATA
dscript-0.3.1.dist-info/WHEEL
dscript-0.3.1.dist-info/entry_points.txt
dscript-0.3.1.dist-info/top_level.txt
dscript-0.3.1.dist-info/RECORD
