Metadata-Version: 2.4
Name: dscript
Version: 0.3.1
Summary: D-SCRIPT: protein-protein interaction prediction
Author-email: Samuel Sledzieski <samsl@mit.edu>
License: MIT
Project-URL: Homepage, http://dscript.csail.mit.edu
Requires-Python: >=3.10
License-File: LICENSE
Requires-Dist: numpy
Requires-Dist: biotite==1.2.0
Requires-Dist: scipy
Requires-Dist: pandas
Requires-Dist: torch>=1.13
Requires-Dist: matplotlib
Requires-Dist: seaborn
Requires-Dist: tqdm
Requires-Dist: scikit-learn
Requires-Dist: h5py
Requires-Dist: huggingface_hub
Requires-Dist: safetensors
Requires-Dist: loguru
Provides-Extra: test
Requires-Dist: pytest; extra == "test"
Requires-Dist: pytest-cov; extra == "test"
Requires-Dist: ruff; extra == "test"
Provides-Extra: dev
Requires-Dist: pytest; extra == "dev"
Requires-Dist: pytest-cov; extra == "dev"
Requires-Dist: ruff; extra == "dev"
Provides-Extra: docs
Requires-Dist: jinja2<3.1; extra == "docs"
Requires-Dist: Sphinx==3.4; extra == "docs"
Requires-Dist: sphinx-rtd-theme==1.0.0; extra == "docs"
Requires-Dist: sphinxcontrib-applehelp==1.0.2; extra == "docs"
Requires-Dist: sphinxcontrib-devhelp==1.0.2; extra == "docs"
Requires-Dist: sphinxcontrib-htmlhelp==1.0.3; extra == "docs"
Requires-Dist: sphinxcontrib-jsmath==1.0.1; extra == "docs"
Requires-Dist: sphinxcontrib-qthelp==1.0.3; extra == "docs"
Requires-Dist: sphinxcontrib-serializinghtml==1.1.4; extra == "docs"
Dynamic: license-file
